CHANGELOG.txt
INSTALL.txt
LICENSE.txt
README.txt
distribute_setup.py
setup.py
NameThatColor.egg-info/PKG-INFO
NameThatColor.egg-info/SOURCES.txt
NameThatColor.egg-info/dependency_links.txt
NameThatColor.egg-info/entry_points.txt
NameThatColor.egg-info/requires.txt
NameThatColor.egg-info/top_level.txt
namethatcolor/NameThatColor.py
namethatcolor/__init__.py
namethatcolor/data/css3.csv
namethatcolor/data/html4.csv
namethatcolor/data/resene.csv