Metadata-Version: 1.0
Name: NameThatColor
Version: 1.0.3
Summary: Find human-readable color names for hex values
Home-page: http://github.com/jdodds/py-name-that-color
Author: Jeremiah Dodds
Author-email: jeremiah.dodds@gmail.com
License: LICENSE.txt
Download-URL: http://github.com/jdodds/py-name-that-color/downloads
Keywords: color colors webcolor hex css html hue saturation lightness red green blue
Platform: UNKNOWN
Classifier: Development Status :: 5 - Production/Stable
Classifier: Environment :: Console
Classifier: Intended Audience :: Developers
Classifier: Intended Audience :: End Users/Desktop
Classifier: License :: OSI Approved :: BSD License
Classifier: Natural Language :: English
Classifier: Operating System :: OS Independent
Classifier: Programming Language :: Python :: 2.6
Classifier: Topic :: Artistic Software
Classifier: Topic :: Multimedia
Classifier: Topic :: Multimedia :: Graphics
Classifier: Topic :: Printing
Classifier: Topic :: Text Processing :: Markup :: HTML
Classifier: Topic :: Utilities
